kivymd_utils/colors/__init__.py
kivymd_utils/coroutine/__init__.py
kivymd_utils/coroutine/coroutineBuilder.py
kivymd_utils/redrawAble/__init__.py
kivymd_utils/redrawAble/notifyListeners.py
kivymd_utils/redrawAble/redrawAble.py
kivymd_utils/router/__init__.py
kivymd_utils/router/error_page.py
kivymd_utils/router/path_utils.py
kivymd_utils/router/route.py
kivymd_utils/router/router.py
kivymd_utils/router/state.py
kivymd_utils-0.16.1.dist-info/LICENSE
kivymd_utils-0.16.1.dist-info/METADATA
kivymd_utils-0.16.1.dist-info/WHEEL
kivymd_utils-0.16.1.dist-info/RECORD
