Metadata-Version: 2.1
Name: kivymd-utils
Version: 0.16.1
Summary: 
Author: MilanR
Author-email: milan.rombouts23@gmail.com
Requires-Python: >=3.11,<4.0
Classifier: Programming Language :: Python :: 3
Classifier: Programming Language :: Python :: 3.11
Classifier: Programming Language :: Python :: 3.12
Requires-Dist: asyncio (>=3.4.3,<4.0.0)
Requires-Dist: kivy (>=2.3.0,<3.0.0)
Requires-Dist: kivymd (>=1.2.0,<2.0.0)
